cirq/__init__.py
cirq/_compat.py
cirq/_compat_test.py
cirq/_import.py
cirq/_version.py
cirq/conftest.py
cirq/py.typed
cirq/type_workarounds.py
cirq/api/__init__.py
cirq/api/google/__init__.py
cirq/api/google/v1/__init__.py
cirq/api/google/v1/operations.proto
cirq/api/google/v1/operations_pb2.py
cirq/api/google/v1/operations_pb2.pyi
cirq/api/google/v1/params.proto
cirq/api/google/v1/params_pb2.py
cirq/api/google/v1/params_pb2.pyi
cirq/api/google/v1/program.proto
cirq/api/google/v1/program_pb2.py
cirq/api/google/v1/program_pb2.pyi
cirq/api/google/v1/proto_test.py
cirq/api/google/v2/__init__.py
cirq/api/google/v2/device.proto
cirq/api/google/v2/device_pb2.py
cirq/api/google/v2/device_pb2.pyi
cirq/api/google/v2/metrics.proto
cirq/api/google/v2/metrics_pb2.py
cirq/api/google/v2/metrics_pb2.pyi
cirq/api/google/v2/program.proto
cirq/api/google/v2/program_pb2.py
cirq/api/google/v2/program_pb2.pyi
cirq/api/google/v2/proto_test.py
cirq/api/google/v2/result.proto
cirq/api/google/v2/result_pb2.py
cirq/api/google/v2/result_pb2.pyi
cirq/api/google/v2/run_context.proto
cirq/api/google/v2/run_context_pb2.py
cirq/api/google/v2/run_context_pb2.pyi
cirq/aqt/__init__.py
cirq/aqt/aqt_device.py
cirq/aqt/aqt_sampler.py
cirq/aqt/aqt_sampler_test.py
cirq/aqt/aqt_simulator_test.py
cirq/circuits/__init__.py
cirq/circuits/_block_diagram_drawer.py
cirq/circuits/_block_diagram_drawer_test.py
cirq/circuits/_box_drawing_character_data.py
cirq/circuits/_box_drawing_character_data_test.py
cirq/circuits/_bucket_priority_queue.py
cirq/circuits/_bucket_priority_queue_test.py
cirq/circuits/circuit.py
cirq/circuits/circuit_dag.py
cirq/circuits/circuit_dag_test.py
cirq/circuits/circuit_test.py
cirq/circuits/insert_strategy.py
cirq/circuits/insert_strategy_test.py
cirq/circuits/optimization_pass.py
cirq/circuits/optimization_pass_test.py
cirq/circuits/qasm_output.py
cirq/circuits/qasm_output_test.py
cirq/circuits/text_diagram_drawer.py
cirq/circuits/text_diagram_drawer_test.py
cirq/contrib/__init__.py
cirq_dev-0.6.0.dev20191029234524.dist-info/LICENSE
cirq_dev-0.6.0.dev20191029234524.dist-info/METADATA
cirq_dev-0.6.0.dev20191029234524.dist-info/WHEEL
cirq_dev-0.6.0.dev20191029234524.dist-info/top_level.txt
cirq_dev-0.6.0.dev20191029234524.dist-info/RECORD
