Metadata-Version: 2.1
Name: cirq-dev
Version: 0.6.0.dev20191029234524
Summary: A framework for creating, editing, and invoking Noisy Intermediate Scale Quantum (NISQ) circuits.
Home-page: http://github.com/quantumlib/cirq
Author: The Cirq Developers
Author-email: cirq@googlegroups.com
License: Apache 2
Platform: UNKNOWN
Requires-Python: >=3.6.0
Requires-Dist: dataclasses
Requires-Dist: google-api-python-client (~=1.6)
Requires-Dist: matplotlib (~=3.0)
Requires-Dist: networkx (==2.3)
Requires-Dist: numpy (~=1.16)
Requires-Dist: pandas
Requires-Dist: protobuf (==3.8.0)
Requires-Dist: requests (~=2.18)
Requires-Dist: sortedcontainers (~=2.0)
Requires-Dist: scipy
Requires-Dist: sympy
Requires-Dist: typing-extensions
Provides-Extra: contrib
Requires-Dist: ply (>=3.4) ; extra == 'contrib'
Requires-Dist: pylatex (~=1.3.0) ; extra == 'contrib'
Requires-Dist: tensorflow (~=1.14) ; extra == 'contrib'
Provides-Extra: dev_env
Requires-Dist: mypy (~=0.701.0) ; extra == 'dev_env'
Requires-Dist: pylint (~=2.3.0) ; extra == 'dev_env'
Requires-Dist: pytest (~=3.8.0) ; extra == 'dev_env'
Requires-Dist: pytest-cov (~=2.5.0) ; extra == 'dev_env'
Requires-Dist: pytest-benchmark (~=3.2.0) ; extra == 'dev_env'
Requires-Dist: yapf (~=0.27.0) ; extra == 'dev_env'
Requires-Dist: grpcio-tools (~=1.24.0) ; extra == 'dev_env'
Requires-Dist: mypy-protobuf (==1.10) ; extra == 'dev_env'
Requires-Dist: twine ; extra == 'dev_env'
Requires-Dist: qiskit (~=0.6.0) ; extra == 'dev_env'
Requires-Dist: pypandoc ; extra == 'dev_env'
Requires-Dist: recommonmark (>=0.4.0) ; extra == 'dev_env'
Requires-Dist: Sphinx ; extra == 'dev_env'
Requires-Dist: sphinx-rtd-theme ; extra == 'dev_env'
Requires-Dist: sphinx-markdown-tables ; extra == 'dev_env'
Requires-Dist: astroid (~=2.1.0) ; extra == 'dev_env'
Requires-Dist: ply (>=3.4) ; extra == 'dev_env'
Requires-Dist: pylatex (~=1.3.0) ; extra == 'dev_env'
Requires-Dist: tensorflow (~=1.14) ; extra == 'dev_env'
